yonoma/__init__.py
yonoma/client.py
yonoma/contacts.py
yonoma/email.py
yonoma/exceptions.py
yonoma/lists.py
yonoma/tags.py
yonoma/version.py
yonoma-1.2.dist-info/METADATA
yonoma-1.2.dist-info/WHEEL
yonoma-1.2.dist-info/top_level.txt
yonoma-1.2.dist-info/RECORD
