Metadata-Version: 2.2
Name: yonoma
Version: 1.2
Summary: A Python client for the Yonoma API
Home-page: https://github.com/YonomaHQ/yonoma-python
Author: YONOMAHQ
Author-email: tools@yonoma.io
Classifier: Programming Language :: Python :: 3
Classifier: License :: OSI Approved :: MIT License
Classifier: Operating System :: OS Independent
Requires-Python: >=3.13.2
Requires-Dist: requests
Dynamic: author
Dynamic: author-email
Dynamic: classifier
Dynamic: description
Dynamic: description-content-type
Dynamic: home-page
Dynamic: requires-dist
Dynamic: requires-python
Dynamic: summary
